bella/__init__.py
bella/modules/detector.py
bella/modules/fs.py
bella/modules/logger.py
bella/modules/text.py
bella/modules/utils.py
bella/modules/utime.py
bella-2.1.5.dist-info/LICENSE
bella-2.1.5.dist-info/WHEEL
bella-2.1.5.dist-info/METADATA
bella-2.1.5.dist-info/RECORD
