Metadata-Version: 2.1
Name: bella
Version: 2.1.5
Summary: BellaPy - A useful helper for any python program
Home-page: https://pypi.org/project/bella
License: MIT
Author: Dong Nguyen
Author-email: ndaidong@gmail.com
Maintainer: Dong Nguyen
Maintainer-email: ndaidong@gmail.com
Requires-Python: >=3.8,<4.0
Classifier: License :: OSI Approved :: MIT License
Classifier: Programming Language :: Python :: 3
Classifier: Programming Language :: Python :: 3.8
Classifier: Programming Language :: Python :: 3.9
Requires-Dist: ujson (>=4.0.1,<5.0.0)
Project-URL: Repository, https://github.com/ndaidong/bellapy
